py_matching_pattern/__init__.py
py_matching_pattern-0.0.3.dist-info/METADATA
py_matching_pattern-0.0.3.dist-info/WHEEL
py_matching_pattern-0.0.3.dist-info/top_level.txt
py_matching_pattern-0.0.3.dist-info/RECORD
