Metadata-Version: 2.1
Name: py-matching-pattern
Version: 0.0.3
Summary: Dynamic Pattern Matching Library
Home-page: https://github.com/diogok/py_matching_pattern
License: MIT
Platform: UNKNOWN
